GiorgisPackage1234/__init__.py
GiorgisPackage1234/base.py
giorgispackage1234-0.0.1.dist-info/licenses/LICENSE
giorgispackage1234-0.0.1.dist-info/METADATA
giorgispackage1234-0.0.1.dist-info/WHEEL
giorgispackage1234-0.0.1.dist-info/top_level.txt
giorgispackage1234-0.0.1.dist-info/RECORD
