Metadata-Version: 2.4
Name: GiorgisPackage1234
Version: 0.0.1
Summary: Tiny package with Base class
Author-email: GiorgiKekelidze <giorgi.kekelidze.3@iliauni.edu.ge>
License: MIT
Requires-Python: >=3.8
License-File: LICENSE
Dynamic: license-file
